lrclibpy/__init__.py
lrclibpy-0.1.0.dist-info/METADATA
lrclibpy-0.1.0.dist-info/WHEEL
lrclibpy-0.1.0.dist-info/RECORD
